boost_aug/__init__.py
boost_aug/boostaug_core.py
experiments/__init__.py
experiments/test.py
boostaug-2.3.5.dist-info/METADATA
boostaug-2.3.5.dist-info/WHEEL
boostaug-2.3.5.dist-info/top_level.txt
boostaug-2.3.5.dist-info/RECORD
