Metadata-Version: 2.1
Name: boostaug
Version: 2.3.5
Home-page: https://github.com/yangheng95/BoostAug
Author: Yang Heng
Author-email: hy345@exeter.ac.uk
License: MIT
Requires-Python: >=3.6
Requires-Dist: pyabsa (>=2.0.10)
Provides-Extra: full
Requires-Dist: textattack ; extra == 'full'
Requires-Dist: nlpaug ; extra == 'full'
Requires-Dist: tensorflow-text ; extra == 'full'
